[
  {"name": "11 BlueLock Creeper", "texture": "11 BlueLock Creeper.png", "price": "1000$", "owner": ""},
  {"name": "Black and Orange 15 years Minecraft", "texture": "Black and Orange 15 years Minecraft.png", "price": "1000$", "owner": ""},
  {"name": "Black and Red 15 years Minecraft", "texture": "Black and Red 15 years Minecraft.png", "price": "1000$", "owner": ""},
  {"name": "Black&Red", "texture": "Black&Red.png", "price": "1000$", "owner": ""},
  {"name": "BlueLock Creeper", "texture": "BlueLock Creeper.png", "price": "1000$", "owner": ""},
  {"name": "Cherry Chocolate", "texture": "Cherry Chocolate.png", "price": "1000$", "owner": ""},
  {"name": "Chocolate face", "texture": "Chocolate face.png", "price": "1000$", "owner": ""},
  {"name": "Chocolate", "texture": "Chocolate.png", "price": "1000$", "owner": ""},
  {"name": "Gray Creeper", "texture": "Gray Creeper.png", "price": "1000$", "owner": ""},
  {"name": "Gray Migrator", "texture": "Gray Migrator.png", "price": "1000$", "owner": ""},
  {"name": "Gray Minecraft Movie", "texture": "Gray Minecraft Movie.png", "price": "1000$", "owner": ""},
  {"name": "Gray", "texture": "Gray.png", "price": "1000$", "owner": ""},
  {"name": "Matheioo's Creeper", "texture": "Matheioo's Creeper.png", "price": "1000$", "owner": ""},
  {"name": "Orange and Purple Creeper", "texture": "Orange and Purple Creeper.png", "price": "1000$", "owner": ""},
  {"name": "Stylish BlueLock Creeper", "texture": "Stylish BlueLock Creeper.png", "price": "1000$", "owner": ""}
]
